pybell/SendNotify.py
pybell/__init__.py
pybell/__main__.py
pybell/constants.py
pybell/Notifiers/Apprise.py
pybell/Notifiers/ExtraParms.py
pybell/Notifiers/Gotify.py
pybell/Notifiers/NTFY.py
pybell/Notifiers/PushBullet.py
pybell/Notifiers/PushOver.py
pybell/Notifiers/Syslog.py
pybell/Notifiers/Telegram.py
pybell/Notifiers/URLSplitInfo.py
pybell/Notifiers/WebCall.py
pybell/Notifiers/__init__.py
mydomuk.pybell-0.0.25.dist-info/METADATA
mydomuk.pybell-0.0.25.dist-info/WHEEL
mydomuk.pybell-0.0.25.dist-info/top_level.txt
mydomuk.pybell-0.0.25.dist-info/RECORD
