Metadata-Version: 2.1
Name: mydomuk.pybell
Version: 0.0.25
Summary: Python Notification Tool
Author: Richard Brent
Requires-Python: >=3.7
Requires-Dist: PyYaml (>=6.0.1)
Requires-Dist: setuptools (>=42)
Requires-Dist: urllib3
Requires-Dist: wheel
